AUTHORS.rst
CONTRIBUTING.rst
HISTORY.rst
LICENSE
MANIFEST.in
README
README.rst
pyms.py
setup.cfg
setup.py
pyms.egg-info/PKG-INFO
pyms.egg-info/SOURCES.txt
pyms.egg-info/dependency_links.txt
pyms.egg-info/not-zip-safe
pyms.egg-info/top_level.txt