Metadata-Version: 1.1
Name: pyms
Version: 0.1.0
Summary: PyMS - A Metastock tool for Python
Home-page: https://github.com/dshipman/pyms
Author: David Shipman
Author-email: unknown@unknown.com
License: BSD
Keywords: pyms
Platform: UNKNOWN
Classifier: Development Status :: 2 - Pre-Alpha
Classifier: Framework :: Django
Classifier: Intended Audience :: Developers
Classifier: License :: OSI Approved :: BSD License
Classifier: Natural Language :: English
Classifier: Programming Language :: Python :: 2
Classifier: Programming Language :: Python :: 2.7
Classifier: Programming Language :: Python :: 3
Classifier: Programming Language :: Python :: 3.3
Classifier: Programming Language :: Python :: 3.4
